[
    {
        "filename": "reqops-or-how-to-become-a-super-product-owner.md",
        "attr": {
            "data-background": "#ffffff"
        }
    },
    "jira-drives-confluence-2.md",
    "jira-drives-confluence-3.md",
    {
        "filename": "index.md",
        "attr": {
            "class": "shadow-box"
        }
    },
    {
        "filename": "next-generation-it.md",
        "attr": {
            "class": "shadow-box"
        }
    },
    {
        "filename": "deploy-scale.md",
        "attr": {
            "data-background": "#ffffff"
        }
    },
    {
        "filename": "scalajs-und-reactjs.md",
        "attr": {
            "data-background": "#ffffff"
        }
    },
    {
        "filename": "microservice-as-a-pattern.md",
        "attr": {
            "data-background": "#ffffff"
        }
    },
    {
        "filename": "visual-regression-testing.md",
        "attr": {
            "data-background": "#ffffff"
        }
    },
    {
        "filename": "devops-service-und-paas.md",
        "attr": {
            "data-background": "#ffffff"
        }
    },
    {
        "filename": "meteor-has-landed.md",
        "attr": {
            "data-background": "#ffffff"
        }
    }
]